[
    {
        "Id": "140101",
        "Name": "教育學系",
        "checked": true,
        "Color": "#98abc5"
    },
    {
        "Id": "140107",
        "Name": "(教育心理與)輔導學系",
        "checked": true,
        "Color": "#7fbc41"
    },
    {
        "Id": "140108",
        "Name": "教育心理與諮商學系",
        "checked": true,
        "Color": "#6b486b"
    },
    {
        "Id": "140120",
        "Name": "課程設計與潛能開發學系",
        "checked": true,
        "Color": "#de77ae"
    },
    {
        "Id": "140121",
        "Name": "國際文教與比較教育學系",
        "checked": true,
        "Color": "#a05d56"
    },
    {
        "Id": "140122",
        "Name": "諮商心理與人力資源發展系",
        "checked": true,
        "Color": "#d0743c"
    },
    {
        "Id": "140124",
        "Name": "諮商心理與人力資源發展系",
        "checked": true,
        "Color": "#c51b7d"
    }
]
